experiment_visualization/__init__.py
experiment_visualization/app.py
experiment_visualization/callbacks.py
experiment_visualization/cli.py
experiment_visualization/handlers.py
experiment_visualization/assets/asset-manifest.json
experiment_visualization/assets/favicon.ico
experiment_visualization/assets/index.html
experiment_visualization/assets/manifest.json
experiment_visualization/assets/static/js/2.effbebe4.chunk.js
experiment_visualization/assets/static/js/2.effbebe4.chunk.js.LICENSE.txt
experiment_visualization/assets/static/js/2.effbebe4.chunk.js.map
experiment_visualization/assets/static/js/main.824854b4.chunk.js
experiment_visualization/assets/static/js/main.824854b4.chunk.js.map
experiment_visualization/assets/static/js/runtime-main.c7369167.js
experiment_visualization/assets/static/js/runtime-main.c7369167.js.map
experiment_visualization/tests/__init__.py
experiment_visualization/tests/app_test.py
experiment_visualization/tests/run_web_server.py
experiment_visualization-0.1.0.dist-info/METADATA
experiment_visualization-0.1.0.dist-info/WHEEL
experiment_visualization-0.1.0.dist-info/entry_points.txt
experiment_visualization-0.1.0.dist-info/top_level.txt
experiment_visualization-0.1.0.dist-info/RECORD
